[
  {
    "id": "anno-wakayama_upper_p086_left-00",
    "type": "Annotation",
    "body": [
      {
        "purpose": "transcribing",
        "value": "藩制一覧表第二（和歌山）"
      },
      {
        "purpose": "modern_jp_reading",
        "value": "藩制一覧表 第二（和歌山）（はんせいいちらん だいに わかやま）"
      },
      {
        "purpose": "english_translation",
        "value": "Table of Domain Institutions, Fascicle 2 (Wakayama) — the running provenance header in the outer margin"
      },
      {
        "purpose": "identifying",
        "value": "藩制一覧表第二（和歌山）"
      }
    ],
    "target": {
      "source": "images/upper_p086_left.jpg",
      "selector": {
        "type": "FragmentSelector",
        "conformsTo": "http://www.w3.org/TR/media-frags/",
        "value": "xywh=pixel:910,1304,66,614"
      }
    }
  },
  {
    "id": "anno-wakayama_upper_p086_left-01",
    "type": "Annotation",
    "body": [
      {
        "purpose": "transcribing",
        "value": "○和歌山藩"
      },
      {
        "purpose": "modern_jp_reading",
        "value": "○和歌山藩（わかやまはん）"
      },
      {
        "purpose": "english_translation",
        "value": "Domain-boundary marker: Wakayama domain — data to the right of this maru-marker belongs to the previous domain; the columns to its left are Wakayama's"
      },
      {
        "purpose": "identifying",
        "value": "○和歌山藩"
      }
    ],
    "target": {
      "source": "images/upper_p086_left.jpg",
      "selector": {
        "type": "FragmentSelector",
        "conformsTo": "http://www.w3.org/TR/media-frags/",
        "value": "xywh=pixel:2622,1407,98,598"
      }
    }
  },
  {
    "id": "anno-wakayama_upper_p086_left-02",
    "type": "Annotation",
    "body": [
      {
        "purpose": "transcribing",
        "value": "草高　五十三萬九千四百六十九石四斗七升七勺"
      },
      {
        "purpose": "modern_jp_reading",
        "value": "草高（くさだか）五三万九四六九石四斗七升七勺"
      },
      {
        "purpose": "english_translation",
        "value": "Assessed nominal yield (kokudaka): 539,469 koku 4 to 7 sho 7 shaku"
      },
      {
        "purpose": "identifying",
        "value": "草高"
      }
    ],
    "target": {
      "source": "images/upper_p086_left.jpg",
      "selector": {
        "type": "FragmentSelector",
        "conformsTo": "http://www.w3.org/TR/media-frags/",
        "value": "xywh=pixel:2475,1070,110,1755"
      }
    }
  },
  {
    "id": "anno-wakayama_upper_p086_left-03",
    "type": "Annotation",
    "body": [
      {
        "purpose": "transcribing",
        "value": "新田高　三百七十二石四斗四升九合一勺"
      },
      {
        "purpose": "modern_jp_reading",
        "value": "新田高（しんでんだか）三七二石四斗四升九合一勺"
      },
      {
        "purpose": "english_translation",
        "value": "Newly reclaimed-field yield: 372 koku 4 to 4 sho 9 go 1 shaku (MASTER's 372.4091 dropped the 四升/sho digit; the scan reads 四斗四升九合一勺 = 372.4491)"
      },
      {
        "purpose": "identifying",
        "value": "新田高"
      }
    ],
    "target": {
      "source": "images/upper_p086_left.jpg",
      "selector": {
        "type": "FragmentSelector",
        "conformsTo": "http://www.w3.org/TR/media-frags/",
        "value": "xywh=pixel:2347,1149,106,1422"
      }
    }
  },
  {
    "id": "anno-wakayama_upper_p086_left-04",
    "type": "Annotation",
    "body": [
      {
        "purpose": "transcribing",
        "value": "正租　米二十六萬八千四百三十八石四升"
      },
      {
        "purpose": "modern_jp_reading",
        "value": "正租（せいそ）米二六万八四三八石四升"
      },
      {
        "purpose": "english_translation",
        "value": "Regular land tax, in rice: 268,438 koku 0 to 4 sho"
      },
      {
        "purpose": "identifying",
        "value": "正租　米"
      }
    ],
    "target": {
      "source": "images/upper_p086_left.jpg",
      "selector": {
        "type": "FragmentSelector",
        "conformsTo": "http://www.w3.org/TR/media-frags/",
        "value": "xywh=pixel:2206,1150,101,1500"
      }
    }
  },
  {
    "id": "anno-wakayama_upper_p086_left-05",
    "type": "Annotation",
    "body": [
      {
        "purpose": "transcribing",
        "value": "金四千五百十五兩一分二朱"
      },
      {
        "purpose": "modern_jp_reading",
        "value": "金（きん）四五一五両一分二朱"
      },
      {
        "purpose": "english_translation",
        "value": "Regular land tax, in gold: 4,515 ryo 1 bu 2 shu"
      },
      {
        "purpose": "identifying",
        "value": "正租　金"
      }
    ],
    "target": {
      "source": "images/upper_p086_left.jpg",
      "selector": {
        "type": "FragmentSelector",
        "conformsTo": "http://www.w3.org/TR/media-frags/",
        "value": "xywh=pixel:2087,1404,85,909"
      }
    }
  },
  {
    "id": "anno-wakayama_upper_p086_left-06",
    "type": "Annotation",
    "body": [
      {
        "purpose": "transcribing",
        "value": "永六拾壹文"
      },
      {
        "purpose": "modern_jp_reading",
        "value": "永（えい）六一文"
      },
      {
        "purpose": "english_translation",
        "value": "Regular land tax, in copper cash (ei): 61 mon"
      },
      {
        "purpose": "identifying",
        "value": "正租　永"
      }
    ],
    "target": {
      "source": "images/upper_p086_left.jpg",
      "selector": {
        "type": "FragmentSelector",
        "conformsTo": "http://www.w3.org/TR/media-frags/",
        "value": "xywh=pixel:1968,1396,73,404"
      }
    }
  },
  {
    "id": "anno-wakayama_upper_p086_left-07",
    "type": "Annotation",
    "body": [
      {
        "purpose": "transcribing",
        "value": "雜稅　米三百七十三石九斗四升貳合六勺五才"
      },
      {
        "purpose": "modern_jp_reading",
        "value": "雑税（ざつぜい）米三七三石九斗四升二合六勺五才"
      },
      {
        "purpose": "english_translation",
        "value": "Miscellaneous taxes, in rice: 373 koku 9 to 4 sho 2 go 6 shaku 5 sai"
      },
      {
        "purpose": "identifying",
        "value": "雜稅　米"
      }
    ],
    "target": {
      "source": "images/upper_p086_left.jpg",
      "selector": {
        "type": "FragmentSelector",
        "conformsTo": "http://www.w3.org/TR/media-frags/",
        "value": "xywh=pixel:1811,1141,107,1669"
      }
    }
  },
  {
    "id": "anno-wakayama_upper_p086_left-08",
    "type": "Annotation",
    "body": [
      {
        "purpose": "transcribing",
        "value": "金壹萬三千三百三十九兩壹分三朱永二十九文八步"
      },
      {
        "purpose": "modern_jp_reading",
        "value": "金（きん）一万三三三九両一分三朱・永二九文八歩"
      },
      {
        "purpose": "english_translation",
        "value": "Miscellaneous taxes, in gold: 13,339 ryo 1 bu 3 shu, plus copper cash (ei) 29 mon 8 bu (a distinct data column MASTER omitted)"
      },
      {
        "purpose": "identifying",
        "value": "雜稅　金"
      }
    ],
    "target": {
      "source": "images/upper_p086_left.jpg",
      "selector": {
        "type": "FragmentSelector",
        "conformsTo": "http://www.w3.org/TR/media-frags/",
        "value": "xywh=pixel:1671,1394,109,1833"
      }
    }
  },
  {
    "id": "anno-wakayama_upper_p086_left-09",
    "type": "Annotation",
    "body": [
      {
        "purpose": "transcribing",
        "value": "鹽　千拾五石五斗八升一合"
      },
      {
        "purpose": "modern_jp_reading",
        "value": "塩（しお）一〇一五石五斗八升一合"
      },
      {
        "purpose": "english_translation",
        "value": "Salt: 1,015 koku 5 to 8 sho 1 go (MASTER's separate 銀/silver entry with this same value is a phantom duplicate of this salt column — no 銀 column exists on the page)"
      },
      {
        "purpose": "identifying",
        "value": "鹽"
      }
    ],
    "target": {
      "source": "images/upper_p086_left.jpg",
      "selector": {
        "type": "FragmentSelector",
        "conformsTo": "http://www.w3.org/TR/media-frags/",
        "value": "xywh=pixel:1554,1391,91,1039"
      }
    }
  },
  {
    "id": "anno-wakayama_upper_p086_left-10",
    "type": "Annotation",
    "body": [
      {
        "purpose": "transcribing",
        "value": "産物税　金二萬八千七百四十三兩三分一朱永四文五步"
      },
      {
        "purpose": "modern_jp_reading",
        "value": "産物税（さんぶつぜい）金二万八七四三両三分一朱・永四文五歩"
      },
      {
        "purpose": "english_translation",
        "value": "Product tax, in gold: 28,743 ryo 3 bu 1 shu, plus copper cash (ei) 4 mon 5 bu (MASTER truncated the 永四文五步 tail)"
      },
      {
        "purpose": "identifying",
        "value": "産物税　金"
      }
    ],
    "target": {
      "source": "images/upper_p086_left.jpg",
      "selector": {
        "type": "FragmentSelector",
        "conformsTo": "http://www.w3.org/TR/media-frags/",
        "value": "xywh=pixel:1400,1138,116,2001"
      }
    }
  },
  {
    "id": "anno-wakayama_upper_p086_left-11",
    "type": "Annotation",
    "body": [
      {
        "purpose": "transcribing",
        "value": "戸數　十萬八千二百四十五戸"
      },
      {
        "purpose": "modern_jp_reading",
        "value": "戸数（こすう）一〇万八二四五戸"
      },
      {
        "purpose": "english_translation",
        "value": "Households: 108,245"
      },
      {
        "purpose": "identifying",
        "value": "戸數"
      }
    ],
    "target": {
      "source": "images/upper_p086_left.jpg",
      "selector": {
        "type": "FragmentSelector",
        "conformsTo": "http://www.w3.org/TR/media-frags/",
        "value": "xywh=pixel:1292,1052,93,1080"
      }
    }
  },
  {
    "id": "anno-wakayama_upper_p086_left-12",
    "type": "Annotation",
    "body": [
      {
        "purpose": "transcribing",
        "value": "人口　四十五萬八千八百二十六人"
      },
      {
        "purpose": "modern_jp_reading",
        "value": "人口（じんこう）四五万八八二六人"
      },
      {
        "purpose": "english_translation",
        "value": "Population (total): 458,826 persons"
      },
      {
        "purpose": "identifying",
        "value": "人口"
      }
    ],
    "target": {
      "source": "images/upper_p086_left.jpg",
      "selector": {
        "type": "FragmentSelector",
        "conformsTo": "http://www.w3.org/TR/media-frags/",
        "value": "xywh=pixel:1155,1146,86,1127"
      }
    }
  },
  {
    "id": "anno-wakayama_upper_p086_left-13",
    "type": "Annotation",
    "body": [
      {
        "purpose": "transcribing",
        "value": "男二十三萬二千六百四十六人"
      },
      {
        "purpose": "modern_jp_reading",
        "value": "男（おとこ）二三万二六四六人"
      },
      {
        "purpose": "english_translation",
        "value": "Population, male: 232,646 persons"
      },
      {
        "purpose": "identifying",
        "value": "男"
      }
    ],
    "target": {
      "source": "images/upper_p086_left.jpg",
      "selector": {
        "type": "FragmentSelector",
        "conformsTo": "http://www.w3.org/TR/media-frags/",
        "value": "xywh=pixel:1172,2410,65,777"
      }
    }
  },
  {
    "id": "anno-wakayama_upper_p086_left-14",
    "type": "Annotation",
    "body": [
      {
        "purpose": "transcribing",
        "value": "女二十二萬六千百八十人"
      },
      {
        "purpose": "modern_jp_reading",
        "value": "女（おんな）二二万六一八〇人"
      },
      {
        "purpose": "english_translation",
        "value": "Population, female: 226,180 persons (232,646 + 226,180 = 458,826, matching the total)"
      },
      {
        "purpose": "identifying",
        "value": "女"
      }
    ],
    "target": {
      "source": "images/upper_p086_left.jpg",
      "selector": {
        "type": "FragmentSelector",
        "conformsTo": "http://www.w3.org/TR/media-frags/",
        "value": "xywh=pixel:1116,2415,63,700"
      }
    }
  },
  {
    "id": "anno-wakayama_upper_p086_left-15",
    "type": "Annotation",
    "body": [
      {
        "purpose": "transcribing",
        "value": "外穢多戸數　五千三百二十六戸"
      },
      {
        "purpose": "modern_jp_reading",
        "value": "外（ほか）穢多戸数（えたこすう）五三二六戸"
      },
      {
        "purpose": "english_translation",
        "value": "Additional: outcaste (eta) households — 5,326"
      },
      {
        "purpose": "identifying",
        "value": "外穢多戸數"
      }
    ],
    "target": {
      "source": "images/upper_p086_left.jpg",
      "selector": {
        "type": "FragmentSelector",
        "conformsTo": "http://www.w3.org/TR/media-frags/",
        "value": "xywh=pixel:1021,1146,72,957"
      }
    }
  },
  {
    "id": "anno-wakayama_upper_p086_left-16",
    "type": "Annotation",
    "body": [
      {
        "purpose": "transcribing",
        "value": "百四十七"
      },
      {
        "purpose": "modern_jp_reading",
        "value": "百四十七（ひゃくよんじゅうしち）＝147"
      },
      {
        "purpose": "english_translation",
        "value": "Printed page number in the bottom margin: 147"
      },
      {
        "purpose": "identifying",
        "value": "頁番号"
      }
    ],
    "target": {
      "source": "images/upper_p086_left.jpg",
      "selector": {
        "type": "FragmentSelector",
        "conformsTo": "http://www.w3.org/TR/media-frags/",
        "value": "xywh=pixel:874,3150,56,203"
      }
    }
  }
]